graphs_csirhall/__init__.py
graphs_csirhall/heapq.py
graphs_csirhall/sp.py
graphs_csirhall-0.0.3.dist-info/METADATA
graphs_csirhall-0.0.3.dist-info/WHEEL
graphs_csirhall-0.0.3.dist-info/RECORD
