Metadata-Version: 2.4
Name: graphs_csirhall
Version: 0.0.3
Summary: A Python package for graph algorithms including Dijkstra's shortest path
Project-URL: Homepage, https://github.com/csirhall/dijkstra-sp
Project-URL: Bug Tracker, https://github.com/csirhall/dijkstra-sp/issues
Author-email: Example Author <author@example.com>
Classifier: License :: OSI Approved :: MIT License
Classifier: Operating System :: OS Independent
Classifier: Programming Language :: Python :: 3
Requires-Python: >=3.7
